pyhwloc/__init__.py
pyhwloc/bitmap.py
pyhwloc/cpukinds.py
pyhwloc/cuda_driver.py
pyhwloc/cuda_runtime.py
pyhwloc/distances.py
pyhwloc/hwobject.py
pyhwloc/memattrs.py
pyhwloc/nvml.py
pyhwloc/py.typed
pyhwloc/topology.py
pyhwloc/utils.py
pyhwloc/hwloc/__init__.py
pyhwloc/hwloc/bitmap.py
pyhwloc/hwloc/core.py
pyhwloc/hwloc/cudadr.py
pyhwloc/hwloc/cudart.py
pyhwloc/hwloc/lib.py
pyhwloc/hwloc/libc.py
pyhwloc/hwloc/linux.py
pyhwloc/hwloc/nvml.py
pyhwloc/hwloc/sched.py
pyhwloc/hwloc/windows.py
pyhwloc/_lib/pyhwloc.dll
pyhwloc/_lib/pyhwloc.lib
pyhwloc/_lib/pyhwloc_cuda.dll
pyhwloc/_lib/pyhwloc_cuda.lib
pyhwloc/_lib/pyhwloc_cudart.dll
pyhwloc/_lib/pyhwloc_cudart.lib
pyhwloc/_lib/pyhwloc_nvml.dll
pyhwloc/_lib/pyhwloc_nvml.lib
pyhwloc/_lib/bin/hwloc.dll
pyhwloc/_lib/lib/hwloc.lib
pyhwloc/_lib/lib/hwloc/hwloc_cuda.dll
pyhwloc-3.0.0.data/data/pyhwloc/_lib/pyhwloc.dll
pyhwloc-3.0.0.data/data/pyhwloc/_lib/pyhwloc.lib
pyhwloc-3.0.0.data/data/pyhwloc/_lib/pyhwloc_cuda.dll
pyhwloc-3.0.0.data/data/pyhwloc/_lib/pyhwloc_cuda.lib
pyhwloc-3.0.0.data/data/pyhwloc/_lib/pyhwloc_cudart.dll
pyhwloc-3.0.0.data/data/pyhwloc/_lib/pyhwloc_cudart.lib
pyhwloc-3.0.0.data/data/pyhwloc/_lib/pyhwloc_nvml.dll
pyhwloc-3.0.0.data/data/pyhwloc/_lib/pyhwloc_nvml.lib
pyhwloc-3.0.0.data/data/pyhwloc/_lib/bin/hwloc.dll
pyhwloc-3.0.0.data/data/pyhwloc/_lib/lib/hwloc.lib
pyhwloc-3.0.0.data/data/pyhwloc/_lib/lib/hwloc/hwloc_cuda.dll
pyhwloc-3.0.0.dist-info/METADATA
pyhwloc-3.0.0.dist-info/WHEEL
pyhwloc-3.0.0.dist-info/licenses/LICENSE
pyhwloc-3.0.0.dist-info/RECORD
