Metadata-Version: 2.4
Name: pyhwloc
Version: 3.0.0
Summary: Python interface of the hwloc library.
Project-URL: source, https://github.com/open-mpi/pyhwloc
Project-URL: documentation, https://pyhwloc.readthedocs.io/
Author-email: Jiaming Yuan <jm.yuan@outlook.com>
Maintainer-email: Jiaming Yuan <jm.yuan@outlook.com>
License: BSD-3-Clause
License-File: LICENSE
Classifier: Intended Audience :: Developers
Classifier: Programming Language :: C
Classifier: Programming Language :: Python
Classifier: Programming Language :: Python :: 3
Classifier: Programming Language :: Python :: 3.12
Classifier: Programming Language :: Python :: 3.13
Classifier: Topic :: Scientific/Engineering
Classifier: Topic :: Software Development
Requires-Python: >=3.12
